versatile_globber/__init__.py
versatile_globber/src/__init__.py
versatile_globber/src/versatile_globber.py
versatile_globber/test/__init__.py
versatile_globber/test/test_utils.py
versatile_globber/test/versatile_globber.py
versatile_globber-0.0.1.dist-info/LICENSE.txt
versatile_globber-0.0.1.dist-info/METADATA
versatile_globber-0.0.1.dist-info/WHEEL
versatile_globber-0.0.1.dist-info/top_level.txt
versatile_globber-0.0.1.dist-info/RECORD
