Metadata-Version: 2.2
Name: versatile_globber
Version: 0.0.1
Summary: This versatile globber helps developers easily look for file that matches any extensions within many folders.
Home-page: https://github.com/ticuong78/versatile_globber
Author: Hùng Cường
Author-email: cuongdayne17@gmail.com
License: MIT
Requires-Python: >=3.13
License-File: LICENSE.txt
Provides-Extra: dev
Requires-Dist: twine>=6.0.0; extra == "dev"
Dynamic: author
Dynamic: author-email
Dynamic: description
Dynamic: description-content-type
Dynamic: home-page
Dynamic: license
Dynamic: provides-extra
Dynamic: requires-python
Dynamic: summary
